pdfposter/__init__.py
pdfposter/cmd.py
pdfposter/i18n.py
pdfposter-0.9.post2.dist-info/licenses/LICENSE-GPLv3.txt
pdfposter-0.9.post2.dist-info/METADATA
pdfposter-0.9.post2.dist-info/WHEEL
pdfposter-0.9.post2.dist-info/entry_points.txt
pdfposter-0.9.post2.dist-info/top_level.txt
pdfposter-0.9.post2.dist-info/zip-safe
pdfposter-0.9.post2.dist-info/RECORD
