Metadata-Version: 2.4
Name: pdfposter
Version: 0.9.post2
Summary: Scale and tile PDF images/pages to print on multiple pages.
Home-page: https://pdfposter.readthedocs.io/
Download-URL: https://pypi.org/project/pdfposter/
Author: Hartmut Goebel
Author-email: h.goebel@crazy-compilers.com
License: GNU General Public License v3 or later (GPLv3+)
Keywords: pdf,poster
Classifier: Development Status :: 5 - Production/Stable
Classifier: Environment :: Console
Classifier: Intended Audience :: Developers
Classifier: Intended Audience :: End Users/Desktop
Classifier: Intended Audience :: System Administrators
Classifier: License :: OSI Approved :: GNU General Public License v3 or later (GPLv3+)
Classifier: Natural Language :: English
Classifier: Operating System :: OS Independent
Classifier: Programming Language :: Python
Classifier: Programming Language :: Python :: 3
Classifier: Programming Language :: Python :: 3.8
Classifier: Programming Language :: Python :: 3.9
Classifier: Programming Language :: Python :: 3.10
Classifier: Programming Language :: Python :: 3.11
Classifier: Programming Language :: Python :: 3.12
Classifier: Programming Language :: Python :: 3.13
Classifier: Topic :: Printing
Classifier: Topic :: Utilities
Requires-Python: >=3.8
License-File: LICENSE-GPLv3.txt
Requires-Dist: pypdf>=5.5
Dynamic: download-url
Dynamic: license-file
